FlashSQL/__init__.py
FlashSQL/db.py
FlashSQL/encoding.py
FlashSQL-0.3.5.dist-info/LICENSE
FlashSQL-0.3.5.dist-info/METADATA
FlashSQL-0.3.5.dist-info/WHEEL
FlashSQL-0.3.5.dist-info/top_level.txt
FlashSQL-0.3.5.dist-info/RECORD
