Metadata-Version: 2.1
Name: FlashSQL
Version: 0.3.5
Summary: A lightweight key-value database using SQLite and APSW.
Home-page: https://github.com/superhexa/FlashSQL
Author: Hexa
Author-email: shexa.developer@gmail.com
Project-URL: Documentation, https://github.com/superhexa/FlashSQL#readme
Project-URL: Source, https://github.com/superhexa/FlashSQL
Project-URL: Tracker, https://github.com/superhexa/FlashSQL/issues
Keywords: database key-value sqlite apsw peformance
Classifier: Development Status :: 3 - Alpha
Classifier: Intended Audience :: Developers
Classifier: License :: OSI Approved :: MIT License
Classifier: Programming Language :: Python :: 3
Classifier: Programming Language :: Python :: 3.6
Classifier: Programming Language :: Python :: 3.7
Classifier: Programming Language :: Python :: 3.8
Classifier: Programming Language :: Python :: 3.9
Classifier: Programming Language :: Python :: 3.10
Classifier: Programming Language :: Python :: 3.11
Classifier: Programming Language :: Python :: 3.12
Classifier: License :: OSI Approved :: MIT License
Classifier: Operating System :: OS Independent
Requires-Python: >=3.6
License-File: LICENSE
Requires-Dist: apsw
